plumber/__init__.py
plumber/behavior.py
plumber/compat.py
plumber/exceptions.py
plumber/instructions.py
plumber/plumber.py
plumber/tests/__init__.py
plumber/tests/globalmetaclass.py
plumber/tests/test_plumber.py
plumber-1.7.dist-info/LICENSE.rst
plumber-1.7.dist-info/METADATA
plumber-1.7.dist-info/WHEEL
plumber-1.7.dist-info/entry_points.txt
plumber-1.7.dist-info/top_level.txt
plumber-1.7.dist-info/zip-safe
plumber-1.7.dist-info/RECORD
