Metadata-Version: 2.1
Name: plumber
Version: 1.7
Summary: An alternative to mixin-based extension of classes.
Home-page: http://github.com/conestack/plumber
Author: Node Contributors
Author-email: dev@conestack.org
License: Simplified BSD
Keywords: class extension mixin alternative
Platform: UNKNOWN
Classifier: Development Status :: 5 - Production/Stable
Classifier: License :: OSI Approved :: Python Software Foundation License
Classifier: Operating System :: OS Independent
Classifier: Topic :: Software Development
Classifier: Programming Language :: Python
Classifier: Programming Language :: Python :: 2.7
Classifier: Programming Language :: Python :: 3.7
Classifier: Programming Language :: Python :: 3.8
Classifier: Programming Language :: Python :: 3.9
Classifier: Programming Language :: Python :: 3.10
Provides-Extra: test
